nic_finance.py
nic_finance-0.0.1.dist-info/LICENSE
nic_finance-0.0.1.dist-info/METADATA
nic_finance-0.0.1.dist-info/WHEEL
nic_finance-0.0.1.dist-info/top_level.txt
nic_finance-0.0.1.dist-info/RECORD
